manage.py
settings.py
b2_utils/__init__.py
b2_utils/context.py
b2_utils/decorators.py
b2_utils/enums.py
b2_utils/fields.py
b2_utils/mails.py
b2_utils/mixins.py
b2_utils/pagination.py
b2_utils/permissions.py
b2_utils/tasks.py
b2_utils/typing.py
b2_utils/validators.py
b2_utils/views.py
b2_utils/baker/__init__.py
b2_utils/faker/__init__.py
b2_utils/faker/providers.py
b2_utils/helpers/__init__.py
b2_utils/helpers/auth.py
b2_utils/serializers/__init__.py
b2_utils/serializers/mixins.py
b2_utils/serializers/relations.py
b2_utils/templatetags/__init__.py
b2_utils/templatetags/b2_utils.py
b2_utils/tests/__init__.py
b2_utils/tests/helpers.py
b2_utils-0.2.10.dist-info/METADATA
b2_utils-0.2.10.dist-info/WHEEL
b2_utils-0.2.10.dist-info/top_level.txt
b2_utils-0.2.10.dist-info/RECORD
